code_collator/__init__.py
code_collator/collate.py
code_collator-0.20.0.dist-info/LICENSE
code_collator-0.20.0.dist-info/METADATA
code_collator-0.20.0.dist-info/WHEEL
code_collator-0.20.0.dist-info/entry_points.txt
code_collator-0.20.0.dist-info/top_level.txt
code_collator-0.20.0.dist-info/RECORD
