Metadata-Version: 2.1
Name: code-collator
Version: 0.20.0
Summary: A CLI tool to aggregate codebase into a single Markdown file
Home-page: https://github.com/tawanda-kembo/code-collator
Author: Tawanda Kembo
Author-email: tawanda@mrkembo.com
Project-URL: Bug Reports, https://github.com/tawanda-kembo/code-collator/issues
Project-URL: Source, https://github.com/tawanda-kembo/code-collator
Keywords: cli,development,documentation
Classifier: Development Status :: 3 - Alpha
Classifier: Intended Audience :: Developers
Classifier: Topic :: Software Development :: Build Tools
Classifier: License :: OSI Approved :: MIT License
Classifier: Programming Language :: Python :: 3
Classifier: Programming Language :: Python :: 3.8
Classifier: Programming Language :: Python :: 3.9
Classifier: Programming Language :: Python :: 3.10
Classifier: Programming Language :: Python :: 3.11
Requires-Python: >=3.6, <4
License-File: LICENSE
Requires-Dist: pygments
